nb2medium/__init__.py
nb2medium/_nbdev.py
nb2medium/convert.py
nb2medium/mediumapi.py
nb2medium/upload.py
nb2medium/nbextension/README.md
nb2medium/nbextension/dialog.png
nb2medium/nbextension/menu_and_button.png
nb2medium/nbextension/nb2medium.js
nb2medium/nbextension/nb2medium.png
nb2medium/nbextension/nb2medium.yml
nb2medium-0.0.2.data/data/etc/jupyter/jupyter_notebook_config.d/nb2medium.json
nb2medium-0.0.2.data/data/etc/jupyter/jupyter_server_config.d/nb2medium.json
nb2medium-0.0.2.data/data/etc/jupyter/nbconfig/notebook.d/nb2medium.json
nb2medium-0.0.2.data/data/share/jupyter/nbextensions/nb2medium/README.md
nb2medium-0.0.2.data/data/share/jupyter/nbextensions/nb2medium/nb2medium.js
nb2medium-0.0.2.data/data/share/jupyter/nbextensions/nb2medium/nb2medium.png
nb2medium-0.0.2.data/data/share/jupyter/nbextensions/nb2medium/nb2medium.yml
nb2medium-0.0.2.dist-info/METADATA
nb2medium-0.0.2.dist-info/WHEEL
nb2medium-0.0.2.dist-info/entry_points.txt
nb2medium-0.0.2.dist-info/top_level.txt
nb2medium-0.0.2.dist-info/RECORD
