Metadata-Version: 2.1
Name: nb2medium
Version: 0.0.2
Summary: Python package and Jupyter extension that enables submitting Medium drafts elegantly from a Jupyter Notebook
Home-page: https://github.com/lucharo/nb2medium/tree/master/
Author: Luis Chaves
Author-email: luis.chaves.rodriguez.6@gmail.com
License: Apache Software License 2.0
Keywords: medium blogging jupyter notebooks python
Platform: UNKNOWN
Classifier: Development Status :: 4 - Beta
Classifier: Intended Audience :: Developers
Classifier: License :: OSI Approved :: Apache Software License
Classifier: Natural Language :: English
Classifier: Programming Language :: Python :: 3.6
Classifier: Programming Language :: Python :: 3.7
Classifier: Programming Language :: Python :: 3.8
Requires-Python: >=3.6
Requires-Dist: requests
Requires-Dist: nbconvert
Requires-Dist: pandas
Requires-Dist: lxml
Requires-Dist: beautifulsoup4
Requires-Dist: fastcore
